phasetorch/__init__.py
phasetorch/mono/__init__.py
phasetorch/mono/_fresmod.py
phasetorch/mono/_inrpr.py
phasetorch/mono/_mullpr.py
phasetorch/mono/_mulmod.py
phasetorch/mono/_nonlpr.py
phasetorch/mono/_nonmod.py
phasetorch/mono/_simtor.py
phasetorch/mono/_sinlpr.py
phasetorch/mono/_sinmod.py
phasetorch/mono/eval.py
phasetorch/mono/pr.py
phasetorch/mono/sim.py
phasetorch/opt/__init__.py
phasetorch/opt/_pytorch_lbfgs/__init__.py
phasetorch/opt/_pytorch_lbfgs/functions/LBFGS.py
phasetorch/opt/_pytorch_lbfgs/functions/__init__.py
phasetorch/opt/_pytorch_lbfgs/functions/utils.py
phasetorch/util/__init__.py
phasetorch/util/_check.py
phasetorch/util/_pad.py
phasetorch/util/_proc.py
phasetorch/util/_projs.py
phasetorch/util/_tutils.py
phasetorch/util/_utils.py
phasetorch-0.2.0.dist-info/LICENSE
phasetorch-0.2.0.dist-info/METADATA
phasetorch-0.2.0.dist-info/NOTICE
phasetorch-0.2.0.dist-info/WHEEL
phasetorch-0.2.0.dist-info/top_level.txt
phasetorch-0.2.0.dist-info/RECORD
