Metadata-Version: 2.1
Name: phasetorch
Version: 0.2.0
Summary: PhaseTorch is a Python package for phase retrieval in X-ray phase contrast computed tomography (XPCT).
Home-page: https://github.com/phasetorch/phasetorch
License: GPL-2.0
Classifier: Programming Language :: Python :: 3
Classifier: Operating System :: OS Independent
License-File: LICENSE
License-File: NOTICE
